snipp_shadowplay/__init__.py
snipp_shadowplay/cli.py
snipp_shadowplay/config.py
snipp_shadowplay/utils.py
snipp_shadowplay/watcher.py
snipp-0.1.5.dist-info/METADATA
snipp-0.1.5.dist-info/WHEEL
snipp-0.1.5.dist-info/entry_points.txt
snipp-0.1.5.dist-info/top_level.txt
snipp-0.1.5.dist-info/RECORD
