Metadata-Version: 2.4
Name: snipp
Version: 0.1.5
Summary: Auto-upload ShadowPlay clips to Snipp.
Home-page: https://github.com/snipp-gg/ShadowPlay
Author: Snipp
Project-URL: Repository, https://github.com/snipp-gg/ShadowPlay
Project-URL: Issues, https://github.com/snipp-gg/ShadowPlay/issues
Classifier: Programming Language :: Python :: 3
Classifier: License :: OSI Approved :: MIT License
Classifier: Operating System :: OS Independent
Requires-Python: >=3.8
Requires-Dist: watchdog
Requires-Dist: requests
Requires-Dist: pyperclip
Requires-Dist: colorama
Dynamic: author
Dynamic: classifier
Dynamic: description
Dynamic: description-content-type
Dynamic: home-page
Dynamic: project-url
Dynamic: requires-dist
Dynamic: requires-python
Dynamic: summary
